<annotation>
	<folder>images</folder>
	<filename>20210905_170537.jpg</filename>
	<path>C:\Users\Abdullah\Desktop\img_label\images\20210905_170537.jpg</path>
	<source>
		<database>Unknown</database>
	</source>
	<size>
		<width>3024</width>
		<height>4032</height>
		<depth>3</depth>
	</size>
	<segmented>0</segmented>
	<object>
		<name>fallen_trees</name>
		<pose>Unspecified</pose>
		<truncated>0</truncated>
		<difficult>0</difficult>
		<bndbox>
			<xmin>1356</xmin>
			<ymin>2016</ymin>
			<xmax>1585</xmax>
			<ymax>2072</ymax>
		</bndbox>
	</object>
	<object>
		<name>fallen_trees</name>
		<pose>Unspecified</pose>
		<truncated>0</truncated>
		<difficult>0</difficult>
		<bndbox>
			<xmin>1597</xmin>
			<ymin>2039</ymin>
			<xmax>1633</xmax>
			<ymax>2066</ymax>
		</bndbox>
	</object>
	<object>
		<name>fallen_trees</name>
		<pose>Unspecified</pose>
		<truncated>0</truncated>
		<difficult>0</difficult>
		<bndbox>
			<xmin>1649</xmin>
			<ymin>2033</ymin>
			<xmax>1705</xmax>
			<ymax>2076</ymax>
		</bndbox>
	</object>
</annotation>
